KrakenOS/Display.py
KrakenOS/HitOnSurf.py
KrakenOS/InterNormalCalc.py
KrakenOS/KrakenSys.py
KrakenOS/LensCat.py
KrakenOS/LibRMS.py
KrakenOS/MathShapesClass.py
KrakenOS/NewthonRaphson.py
KrakenOS/PSFCalc.py
KrakenOS/PSFMap.py
KrakenOS/PhaseCalc.py
KrakenOS/Physics.py
KrakenOS/PhysicsClass.py
KrakenOS/Prerequisites3D.py
KrakenOS/PupilTool.py
KrakenOS/RayKeeper.py
KrakenOS/SeidelTool.py
KrakenOS/SetupClass.py
KrakenOS/SourceRand.py
KrakenOS/SphericalPSFCalc.py
KrakenOS/SurfBlockClass.py
KrakenOS/SurfClass.py
KrakenOS/SurfTools.py
KrakenOS/SystemTools.py
KrakenOS/TraceLoopTool.py
KrakenOS/UDA.py
KrakenOS/WavePlot.py
KrakenOS/WavefrontFit.py
KrakenOS/__init__.py
KrakenOS/AstroAtmosphere/.DS_Store
KrakenOS/AstroAtmosphere/AtmosP 3.py
KrakenOS/AstroAtmosphere/AtmosP.py
KrakenOS/AstroAtmosphere/AtmosP.txt
KrakenOS/AstroAtmosphere/__init__.py
KrakenOS/AstroAtmosphere/ciddorModel.py
KrakenOS/AstroAtmosphere/dispersionModels.py
KrakenOS/AstroAtmosphere/misc.py
KrakenOS/AstroAtmosphere/neoslalib.py
KrakenOS/AstroAtmosphere/observatories.py
KrakenOS/AstroAtmosphere/refractionModels.py
KrakenOS/AstroAtmosphere/refractivityModels.py
KrakenOS/AstroAtmosphere/__pycache__/__init__.cpython-38.pyc
KrakenOS/AstroAtmosphere/__pycache__/ciddorModel.cpython-38.pyc
KrakenOS/AstroAtmosphere/__pycache__/dispersionModels.cpython-38.pyc
KrakenOS/AstroAtmosphere/__pycache__/misc.cpython-38.pyc
KrakenOS/AstroAtmosphere/__pycache__/neoslalib.cpython-38.pyc
KrakenOS/AstroAtmosphere/__pycache__/observatories.cpython-38.pyc
KrakenOS/AstroAtmosphere/__pycache__/refractionModels.cpython-38.pyc
KrakenOS/AstroAtmosphere/__pycache__/refractivityModels.cpython-38.pyc
KrakenOS/AstroAtmosphere/data/1976USSA.txt
KrakenOS/Cat/Alum.csv
KrakenOS/Cat/Gold.csv
KrakenOS/Cat/HOYA20220711_include_obsolete.agf
KrakenOS/Cat/SCHOTT-2.AGF
KrakenOS/Cat/SCHOTT.AGF
KrakenOS/Cat/UTILIDADES.AGF
KrakenOS/Cat/archer.agf
KrakenOS/Cat/arton.agf
KrakenOS/Cat/birefringent.agf
KrakenOS/Cat/cdgm.agf
KrakenOS/Cat/corning.agf
krakenos-1.0.0.24.dist-info/licenses/LICENSE.txt
krakenos-1.0.0.24.dist-info/METADATA
krakenos-1.0.0.24.dist-info/WHEEL
krakenos-1.0.0.24.dist-info/top_level.txt
krakenos-1.0.0.24.dist-info/RECORD
