Metadata-Version: 2.4
Name: KrakenOS
Version: 1.0.0.24
Summary: Optical Simulation and ray tracing 
Home-page: https://github.com/Garchupiter/Kraken-Optical-Simulator
Download-URL: https://github.com/Garchupiter/Kraken-Optical-Simulator
Author: joel Herrera et al.
Author-email: joel@astro.unam.mx
License: GNU General Public License v3.0
Keywords: Optical,Simulator,lens
License-File: LICENSE.txt
Requires-Dist: pyvista
Requires-Dist: PyVTK
Requires-Dist: vtk
Requires-Dist: numpy
Requires-Dist: scipy
Requires-Dist: matplotlib
Requires-Dist: csv342
Requires-Dist: pandas
Dynamic: author
Dynamic: author-email
Dynamic: download-url
Dynamic: home-page
Dynamic: keywords
Dynamic: license
Dynamic: license-file
Dynamic: requires-dist
Dynamic: summary
